ap_mcp_server/__init__.py
ap_mcp_server/cli.py
ap_mcp_server/client.py
ap_mcp_server/server.py
ap_mcp_server-0.1.0.dist-info/METADATA
ap_mcp_server-0.1.0.dist-info/WHEEL
ap_mcp_server-0.1.0.dist-info/entry_points.txt
ap_mcp_server-0.1.0.dist-info/RECORD
