Metadata-Version: 2.4
Name: ap-mcp-server
Version: 0.1.0
Summary: AP Materials leave MCP server & client
Project-URL: Homepage, https://github.com/yourname/ap-mcp-server
Requires-Python: >=3.10
Requires-Dist: httpx
Requires-Dist: mcp[cli]>=1.0.0
Requires-Dist: pydantic
